<?xml version="1.0" encoding="utf-8" ?><dwsync><file name="Abstract.php" server="beztolkotni.ru//httpdocs/beztolkotni.ru/" local="130698178420000000" remote="130699371600000000" Dst="-1" /><file name="cacerts.pem" server="beztolkotni.ru//httpdocs/beztolkotni.ru/" local="130698178420000000" remote="130699371600000000" Dst="-1" /><file name="Curl.php" server="beztolkotni.ru//httpdocs/beztolkotni.ru/" local="130698178420000000" remote="130699371600000000" Dst="-1" /><file name="Exception.php" server="beztolkotni.ru//httpdocs/beztolkotni.ru/" local="130698178420000000" remote="130699371600000000" Dst="-1" /><file name="Stream.php" server="beztolkotni.ru//httpdocs/beztolkotni.ru/" local="130698178420000000" remote="130699371600000000" Dst="-1" /><file name="Curl.php" server="batiskaff.ru//httpdocs/beztolkotni.ru/" local="3510835693" remote="318763443901204872" Dst="-1" /><file name="Abstract.php" server="batiskaff.ru//httpdocs/beztolkotni.ru/" local="3510835693" remote="318763443901204872" Dst="-1" /><file name="cacerts.pem" server="batiskaff.ru//httpdocs/beztolkotni.ru/" local="3510835693" remote="318763443901204872" Dst="-1" /><file name="Exception.php" server="batiskaff.ru//httpdocs/beztolkotni.ru/" local="3510835693" remote="318763443901204872" Dst="-1" /><file name="Stream.php" server="batiskaff.ru//httpdocs/beztolkotni.ru/" local="3510835693" remote="318763443901204872" Dst="-1" /></dwsync>